airflow/providers/normalizer/__init__.py
airflow/providers/normalizer/operators/__init__.py
airflow/providers/normalizer/operators/normalizer.py
airflow/providers/normalizer/operators/queries.py
airflow/providers/normalizer/operators/utils.py
apache_airflow_providers_normalizer-1.0.0.dist-info/LICENSE
apache_airflow_providers_normalizer-1.0.0.dist-info/METADATA
apache_airflow_providers_normalizer-1.0.0.dist-info/WHEEL
apache_airflow_providers_normalizer-1.0.0.dist-info/top_level.txt
apache_airflow_providers_normalizer-1.0.0.dist-info/RECORD
