Metadata-Version: 2.1
Name: apache-airflow-providers-normalizer
Version: 1.0.0
Summary: Provider for Apache Airflow. Implements json normalization to nested tables by yaml specification
Author-email: woodocat <woodocat@gmail.com>
Project-URL: Homepage, https://github.com/woodocat/apache-airflow-providers-normalizer
Project-URL: Bug Tracker, https://github.com/woodocat/apache-airflow-providers-normalizer/issues
Classifier: Programming Language :: Python :: 3
Classifier: License :: OSI Approved :: Apache Software License
Classifier: Operating System :: OS Independent
Classifier: Framework :: Apache Airflow
Classifier: Framework :: Apache Airflow :: Provider
Requires-Python: >=3.8
License-File: LICENSE
Requires-Dist: apache-airflow >=2.1.0
Requires-Dist: pyyaml
